divert/__init__.py
divert/core.py
divert/flow.py
divert/targeted.py
divert-0.1.0.dist-info/METADATA
divert-0.1.0.dist-info/WHEEL
divert-0.1.0.dist-info/top_level.txt
divert-0.1.0.dist-info/RECORD
