Metadata-Version: 2.1
Name: divert
Version: 0.1.0
Summary: Divert the execution flow.
Author-email: Ben <22123881+simonsben@users.noreply.github.com>
Keywords: execution,flow,divert
Classifier: Programming Language :: Python :: 3
Requires-Python: >=3.10
